clear_cut/__init__.py
clear_cut/clear_cutter.py
clear_cut/images/Bob.jpeg
clear_cut/images/__init__.py
clear_cut/utils/__init__.py
clear_cut/utils/constants.py
clear_cut/utils/edge_utility.py
clear_cut/utils/graph_tools.py
clear_cut/utils/tracers/__init__.py
clear_cut/utils/tracers/base.py
clear_cut/utils/tracers/gradient.py
clear_cut/utils/tracers/texture.py
documentation/visuals/__init__.py
documentation/visuals/edge_id_aids/__init__.py
documentation/visuals/pooling_aids/__init__.py
clear_cut-1.4.2.dist-info/LICENSE
clear_cut-1.4.2.dist-info/METADATA
clear_cut-1.4.2.dist-info/WHEEL
clear_cut-1.4.2.dist-info/top_level.txt
clear_cut-1.4.2.dist-info/RECORD
