Metadata-Version: 2.1
Name: clear-cut
Version: 1.4.2
Summary: Number crunching backend to extract edges from a provided image
Home-page: https://github.com/chrispdharman/clear-cut
Author: Christopher Harman
Author-email: christopher.p.d.harman@gmail.com
License: MIT
Platform: UNKNOWN
Classifier: Programming Language :: Python :: 3
Classifier: Operating System :: OS Independent
Classifier: Intended Audience :: Information Technology
Classifier: Natural Language :: English
Classifier: Topic :: Scientific/Engineering
Requires-Python: >=3.6
Requires-Dist: numpy (==1.18.5)
Requires-Dist: Pillow (==7.1.2)
Requires-Dist: scikit-image (==0.17.2)
